autoswitch/__init__.py
autoswitch/__main__.py
autoswitch/cli.py
autoswitch/exceptions.py
autoswitch/network.py
autoswitch/utils.py
tests/__init__.py
tests/test_parser.py
autoswitch-0.0.1.2.dist-info/LICENSE
autoswitch-0.0.1.2.dist-info/METADATA
autoswitch-0.0.1.2.dist-info/WHEEL
autoswitch-0.0.1.2.dist-info/top_level.txt
autoswitch-0.0.1.2.dist-info/RECORD
