Metadata-Version: 2.1
Name: autoswitch
Version: 0.0.1.2
Summary: Configure Cisco devices
Home-page: UNKNOWN
Author: Kyle Davis
Author-email: contact@kyledavis.dev
License: UNKNOWN
Project-URL: Bug Tracker, https://github.com/kyledavis124/AutoSwitch/issues
Project-URL: Github, https://github.com/kyledavis124/AutoSwitch
Platform: UNKNOWN
Classifier: Programming Language :: Python :: 3
Classifier: License :: OSI Approved :: GNU General Public License v3 (GPLv3)
Classifier: Operating System :: OS Independent
Requires-Python: >=3.8
Requires-Dist: netmiko
